iotproj/__init__.py
iotproj/iotproj_cli.py
iotproj/iotproj_lib.py
iotproj-0.0.1.dist-info/LICENSE
iotproj-0.0.1.dist-info/METADATA
iotproj-0.0.1.dist-info/WHEEL
iotproj-0.0.1.dist-info/entry_points.txt
iotproj-0.0.1.dist-info/top_level.txt
iotproj-0.0.1.dist-info/RECORD
